{"section_number":"151.14","edition_id":"1","section_id":"467","structure_id":"38","catch_line":"Filing Of Application For Rent Adjustments, Requests For Hearing, And Appeals.","history":"","full_text":"\u00a0 FILING OF APPLICATION FOR RENT ADJUSTMENTS, REQUESTS FOR HEARING, AND APPEALS.\n\n\tA.\tFiling Date.\u00a0 (Amended by Ord. No. 165,251, Eff. 11\/20\/89.)\u00a0 An application for rent adjustment, request for hearing, appeal or re-rental certificate shall be considered as filed on the date it has been completed in accordance with the applicable rules and regulations, and received together with any required filing fee by the Department. If at any time during the processing of an application it is determined that an application has been improperly prepared, or requires additional information not submitted in accordance with the rules and regulations, the time limits specified within this chapter shall be suspended and not continue to run until the application has been rectified or the omitted information furnished upon written notification to the applicant.\n\n\tB.\tPlace of Filing.\u00a0 Whenever the provisions of this chapter provide that applications or requests for hearing or appeals be filed in the office of the Department, such applications or requests for hearing or appeals may be filed in any of the branch offices of the Department.\n\n\tC.\tAn application fee required under this section may be waived by the Department for any individual who files a declaration stating that he or she annually earns no more than 50% of the median income for the Los Angeles area. The declaration shall state the above information is true and correct.\u00a0 The median is to be determined by the standards utilized by the Housing Authority of the City of Los Angeles acting pursuant to HUD relations. (Amended by Ord. No. 160,791, Eff. 2\/10\/86.)\n\n\tD.\tIf a hearing officer determines, based on clear and convincing evidence, that an applicant has willfully or knowingly with the intent to deceive, made or caused to be made a false statement or representation, or knowingly failed to disclose a material fact, in connection with any application under consideration by the hearing officer, then the hearing officer may deny the application.\u00a0 Any determination by the hearing officer based on this subsection shall be appealable to the Rent Adjustment Commission.\u00a0 (Added by Ord. No. 160,791, Eff. 2\/10\/86.)\n\n\tE.\tFor purposes of this chapter, if an application, request for appeal or request for hearing is mailed to the Department, it is deemed to be received as established by the date of the postmark affixed on an envelope properly addressed to the Department.\u00a0 (Added by Ord. No. 160,791, Eff. 2\/10\/86.)","order_by":"14","ancestry":{"1":{"id":"38","name":"Rent Stabilization Ordinance","identifier":"1","label":"article","url":"\/15\/1\/"},"2":{"id":"37","name":"Rent Stabilization Ordinance","identifier":"15","label":"chapter","url":"\/15\/"}},"structure_contents":{"0":{"id":"1697","structure_id":"38","section_number":"151.00","catch_line":"Title.","url":"\/151.00\/","token":"151.00"},"1":{"id":"1881","structure_id":"38","section_number":"151.01","catch_line":"Declaration Of Purpose.","url":"\/151.01\/","token":"151.01"},"2":{"id":"2461","structure_id":"38","section_number":"151.02","catch_line":"Definitions.","url":"\/151.02\/","token":"151.02"},"3":{"id":"1905","structure_id":"38","section_number":"151.03","catch_line":"The Rent Adjustment Commission.","url":"\/151.03\/","token":"151.03"},"4":{"id":"2887","structure_id":"38","section_number":"151.04","catch_line":"Restriction On Rents.","url":"\/151.04\/","token":"151.04"},"5":{"id":"2613","structure_id":"38","section_number":"151.05","catch_line":"Registration, Notification Of Tenants, Posting Of Notice And Payment Of Fees.","url":"\/151.05\/","token":"151.05"},"6":{"id":"1401","structure_id":"38","section_number":"151.05.1","catch_line":"Passthrough Of Surcharge For The Systematic Code Enforcement Fee.","url":"\/151.05.1\/","token":"151.05.1"},"7":{"id":"1394","structure_id":"38","section_number":"151.06","catch_line":"Automatic Adjustments.","url":"\/151.06\/","token":"151.06"},"8":{"id":"1165","structure_id":"38","section_number":"151.06.02","catch_line":"Payment Of Interest On Security Deposits.","url":"\/151.06.02\/","token":"151.06.02"},"9":{"id":"2392","structure_id":"38","section_number":"151.06.1","catch_line":"Smoke Detectors.","url":"\/151.06.1\/","token":"151.06.1"},"10":{"id":"3311","structure_id":"38","section_number":"151.06.2","catch_line":"Surcharge For Water Conservation Assessment.","url":"\/151.06.2\/","token":"151.06.2"},"11":{"id":"3423","structure_id":"38","section_number":"151.06.5","catch_line":"Reductions In Rent.","url":"\/151.06.5\/","token":"151.06.5"},"12":{"id":"66","structure_id":"38","section_number":"151.07","catch_line":"Authority Of The Department And The Commission To Grant Individual Rent Adjustments.","url":"\/151.07\/","token":"151.07"},"13":{"id":"3940","structure_id":"38","section_number":"151.08","catch_line":"Authority Of Commission To Regulate By Class.","url":"\/151.08\/","token":"151.08"},"14":{"id":"1253","structure_id":"38","section_number":"151.09","catch_line":"Evictions.","url":"\/151.09\/","token":"151.09"},"15":{"id":"2643","structure_id":"38","section_number":"151.10","catch_line":"Remedies.","url":"\/151.10\/","token":"151.10"},"16":{"id":"3461","structure_id":"38","section_number":"151.11","catch_line":"Refusal Of A Tenant To Pay.","url":"\/151.11\/","token":"151.11"},"17":{"id":"1361","structure_id":"38","section_number":"151.12","catch_line":"Operative Date.","url":"\/151.12\/","token":"151.12"},"18":{"id":"3106","structure_id":"38","section_number":"151.13","catch_line":"Minor Errors In Payment.","url":"\/151.13\/","token":"151.13"},"19":{"id":"467","structure_id":"38","section_number":"151.14","catch_line":"Filing Of Application For Rent Adjustments, Requests For Hearing, And Appeals.","url":"\/151.14\/","token":"151.14"},"20":{"id":"2596","structure_id":"38","section_number":"151.15","catch_line":"151.15.Penalties For Late Registration And For Failure To Post Notice That Property Is Subject To The Rent Stabilization Ordinance.","url":"\/151.15\/","token":"151.15"},"21":{"id":"2542","structure_id":"38","section_number":"151.16","catch_line":"Research Services.","url":"\/151.16\/","token":"151.16"},"22":{"id":"3174","structure_id":"38","section_number":"151.18","catch_line":"Additional Services Contracts.","url":"\/151.18\/","token":"151.18"},"23":{"id":"909","structure_id":"38","section_number":"151.19","catch_line":"Review Of Ordinance.","url":"\/151.19\/","token":"151.19"},"24":{"id":"2430","structure_id":"38","section_number":"151.20","catch_line":"Temporary Eviction Controls And Rent Reductions For Mobile Homes Damaged In The January, 1994 Earthquake.","url":"\/151.20\/","token":"151.20"},"25":{"id":"2740","structure_id":"38","section_number":"151.21","catch_line":"Hurricane Katrina And Hurricane Rita Temporary Relief Program.","url":"\/151.21\/","token":"151.21"},"26":{"id":"299","structure_id":"38","section_number":"151.22","catch_line":"Ellis Act Provisions - Statement Of Purpose And Effect.","url":"\/151.22\/","token":"151.22"},"27":{"id":"3047","structure_id":"38","section_number":"151.23","catch_line":"Ellis Act Provisions - Required Notice.","url":"\/151.23\/","token":"151.23"},"28":{"id":"2552","structure_id":"38","section_number":"151.24","catch_line":"Ellis Act Provisions - Notification To Department Of Intent To Re-Rent Unit.","url":"\/151.24\/","token":"151.24"},"29":{"id":"1480","structure_id":"38","section_number":"151.25","catch_line":"Ellis Act Provisions - Civil Penalties For Offering Units For Rent Within Two Years Of Withdrawal.","url":"\/151.25\/","token":"151.25"},"30":{"id":"1337","structure_id":"38","section_number":"151.26","catch_line":"Ellis Act Provisions - Regulation Of Property On Re-Offer For Rent Or Lease After Withdrawal.","url":"\/151.26\/","token":"151.26"},"31":{"id":"1267","structure_id":"38","section_number":"151.27","catch_line":"Ellis Act Provisions - Re-Rental Rights Of Displaced Tenants.","url":"\/151.27\/","token":"151.27"},"32":{"id":"2909","structure_id":"38","section_number":"151.28","catch_line":"Ellis Act Provisions - Rental Of Replacement Units.","url":"\/151.28\/","token":"151.28"},"33":{"id":"71","structure_id":"38","section_number":"151.29","catch_line":"Regulation Of Leases In Mobilehome Parks.","url":"\/151.29\/","token":"151.29"},"34":{"id":"3924","structure_id":"38","section_number":"151.30","catch_line":"Evictions For Owner, Family, Or Resident Manager\nOccupancy.","url":"\/151.30\/","token":"151.30"}},"next_section":{"id":"2596","structure_id":"38","section_number":"151.15","catch_line":"151.15.Penalties For Late Registration And For Failure To Post Notice That Property Is Subject To The Rent Stabilization Ordinance.","url":"\/151.15\/","token":"151.15"},"metadata":false,"references":false,"url":"\/151.14\/","token":"151.14","formats":{"txt":"\/151.14.txt","json":"\/151.14.xml"},"dublin_core":{"Title":"Filing Of Application For Rent Adjustments, Requests For Hearing, And Appeals.","Type":"Text","Format":"text\/html","Identifier":"\u00a7 151.14","Relation":"Los Angeles Municipal Code"},"plain_text":"                            LOS ANGELES MUNICIPAL CODE\n\nFILING OF APPLICATION FOR RENT ADJUSTMENTS, REQUESTS FOR HEARING, AND APPEALS.\n(\u00a7 151.14)\n\n\u00a0 FILING OF APPLICATION FOR RENT ADJUSTMENTS, REQUESTS FOR HEARING, AND\nAPPEALS.\tA.\tFiling Date.\u00a0 (Amended by Ord. No. 165,251, Eff. 11\/20\/89.)\u00a0 An\napplication for rent adjustment, request for hearing, appeal or re-rental\ncertificate shall be considered as filed on the date it has been completed in\naccordance with the applicable rules and regulations, and received together with\nany required filing fee by the Department. If at any time during the processing\nof an application it is determined that an application has been improperly\nprepared, or requires additional information not submitted in accordance with\nthe rules and regulations, the time limits specified within this chapter shall\nbe suspended and not continue to run until the application has been rectified or\nthe omitted information furnished upon written notification to the\napplicant.\tB.\tPlace of Filing.\u00a0 Whenever the provisions of this chapter provide\nthat applications or requests for hearing or appeals be filed in the office of\nthe Department, such applications or requests for hearing or appeals may be\nfiled in any of the branch offices of the Department.\tC.\tAn application fee\nrequired under this section may be waived by the Department for any individual\nwho files a declaration stating that he or she annually earns no more than 50%\nof the median income for the Los Angeles area. The declaration shall state the\nabove information is true and correct.\u00a0 The median is to be determined by the\nstandards utilized by the Housing Authority of the City of Los Angeles acting\npursuant to HUD relations. (Amended by Ord. No. 160,791, Eff. 2\/10\/86.)\tD.\tIf a\nhearing officer determines, based on clear and convincing evidence, that an\napplicant has willfully or knowingly with the intent to deceive, made or caused\nto be made a false statement or representation, or knowingly failed to disclose\na material fact, in connection with any application under consideration by the\nhearing officer, then the hearing officer may deny the application.\u00a0 Any\ndetermination by the hearing officer based on this subsection shall be\nappealable to the Rent Adjustment Commission.\u00a0 (Added by Ord. No. 160,791, Eff.\n2\/10\/86.)\tE.\tFor purposes of this chapter, if an application, request for appeal\nor request for hearing is mailed to the Department, it is deemed to be received\nas established by the date of the postmark affixed on an envelope properly\naddressed to the Department.\u00a0 (Added by Ord. No. 160,791, Eff. 2\/10\/86.)\n","html":"\n\t\t\t\t\t<section><p>\u00a0 FILING OF APPLICATION FOR RENT ADJUSTMENTS, REQUESTS FOR <span class=\"dictionary\">HEARING<\/span>, AND <span class=\"dictionary\">APPEALS<\/span>.<br \/><br \/>\tA.\tFiling Date.\u00a0 (Amended by Ord. No. 165,251, Eff. 11\/20\/89.)\u00a0 An application for rent adjustment, request for <span class=\"dictionary\">hearing<\/span>, <span class=\"dictionary\">appeal<\/span> or re-rental certificate shall be considered as filed on the date it has been completed in accordance with the applicable rules and regulations, and received together with any required filing fee by the Department. If at any time during the processing of an application it is determined that an application has been improperly prepared, or requires additional information not submitted in accordance with the rules and regulations, the time limits specified within this chapter shall be suspended and not continue to run until the application has been rectified or the omitted information furnished upon written notification to the applicant.<br \/><br \/>\tB.\tPlace of Filing.\u00a0 Whenever the provisions of this chapter provide that applications or requests for <span class=\"dictionary\">hearing<\/span> or <span class=\"dictionary\">appeals<\/span> be filed in the office of the Department, such applications or requests for <span class=\"dictionary\">hearing<\/span> or <span class=\"dictionary\">appeals<\/span> may be filed in any of the branch offices of the Department.<br \/><br \/>\tC.\tAn application fee required under this section may be waived by the Department for any individual who files a declaration stating that he or she annually earns no more than 50% of the median income for the Los Angeles area. The declaration shall state the above information is true and correct.\u00a0 The median is to be determined by the standards utilized by the Housing Authority of the City of Los Angeles acting pursuant to HUD relations. (Amended by Ord. No. 160,791, Eff. 2\/10\/86.)<br \/><br \/>\tD.\tIf a <span class=\"dictionary\">hearing<\/span> officer determines, based on clear and convincing <span class=\"dictionary\">evidence<\/span>, that an applicant has willfully or knowingly with the <span class=\"dictionary\">intent<\/span> to deceive, made or caused to be made a false statement or representation, or knowingly failed to disclose a <span class=\"dictionary\">material<\/span> <span class=\"dictionary\">fact<\/span>, in connection with any application under consideration by the <span class=\"dictionary\">hearing<\/span> officer, then the <span class=\"dictionary\">hearing<\/span> officer may deny the application.\u00a0 Any determination by the <span class=\"dictionary\">hearing<\/span> officer based on this subsection shall be appealable to the Rent Adjustment Commission.\u00a0 (Added by Ord. No. 160,791, Eff. 2\/10\/86.)<br \/><br \/>\tE.\tFor purposes of this chapter, if an application, request for <span class=\"dictionary\">appeal<\/span> or request for <span class=\"dictionary\">hearing<\/span> is mailed to the Department, it is deemed to be received as established by the date of the postmark affixed on an envelope properly addressed to the Department.\u00a0 (Added by Ord. No. 160,791, Eff. 2\/10\/86.)<\/p><\/section>","previous_section":{"id":"3106","structure_id":"38","section_number":"151.13","catch_line":"Minor Errors In Payment.","url":"\/151.13\/","token":"151.13"},"text":{"0":{"id":"460","text":"\u00a0 FILING OF APPLICATION FOR RENT ADJUSTMENTS, REQUESTS FOR HEARING, AND APPEALS.\tA.\tFiling Date.\u00a0 (Amended by Ord. No. 165,251, Eff. 11\/20\/89.)\u00a0 An application for rent adjustment, request for hearing, appeal or re-rental certificate shall be considered as filed on the date it has been completed in accordance with the applicable rules and regulations, and received together with any required filing fee by the Department. If at any time during the processing of an application it is determined that an application has been improperly prepared, or requires additional information not submitted in accordance with the rules and regulations, the time limits specified within this chapter shall be suspended and not continue to run until the application has been rectified or the omitted information furnished upon written notification to the applicant.\tB.\tPlace of Filing.\u00a0 Whenever the provisions of this chapter provide that applications or requests for hearing or appeals be filed in the office of the Department, such applications or requests for hearing or appeals may be filed in any of the branch offices of the Department.\tC.\tAn application fee required under this section may be waived by the Department for any individual who files a declaration stating that he or she annually earns no more than 50% of the median income for the Los Angeles area. The declaration shall state the above information is true and correct.\u00a0 The median is to be determined by the standards utilized by the Housing Authority of the City of Los Angeles acting pursuant to HUD relations. (Amended by Ord. No. 160,791, Eff. 2\/10\/86.)\tD.\tIf a hearing officer determines, based on clear and convincing evidence, that an applicant has willfully or knowingly with the intent to deceive, made or caused to be made a false statement or representation, or knowingly failed to disclose a material fact, in connection with any application under consideration by the hearing officer, then the hearing officer may deny the application.\u00a0 Any determination by the hearing officer based on this subsection shall be appealable to the Rent Adjustment Commission.\u00a0 (Added by Ord. No. 160,791, Eff. 2\/10\/86.)\tE.\tFor purposes of this chapter, if an application, request for appeal or request for hearing is mailed to the Department, it is deemed to be received as established by the date of the postmark affixed on an envelope properly addressed to the Department.\u00a0 (Added by Ord. No. 160,791, Eff. 2\/10\/86.)","type":"section","prefixes":[""],"prefix":"","entire_prefix":"","prefix_anchor":"","level":1}}}