<?xml version="1.0"?>
<law><section_number>114.04</section_number><edition_id>1</edition_id><section_id>2293</section_id><structure_id>84</structure_id><catch_line>Audible Signaling Devices.</catch_line><history></history><full_text>&#xA0; AUDIBLE SIGNALING DEVICES.
	(Added by Ord. No. 161,574, Eff. 9/8/86.)

	It shall be unlawful for any person, within any residential zone of the City or within 500 feet thereof, to sound, blow, or operate any audible signaling device, including sequential airhorns or electronically operated vehicular loud speaker music devices, which can be heard for a distance greater than 200 feet for any purpose.&#xA0; Violation of this section shall constitute an infraction&#xA0; This section does not address horn or warning devices regulated in Article 1 of Chapter 5 of Division 12 of the Vehicle Code of the State of California, commencing at Section 27000.&#xA0; (Last sentence amended by Ord. No. 165.191, Eff. 10/23/89.)</full_text><order_by>04</order_by><ancestry><unit id="84" label="article"><name>Vehicles</name><identifier>4</identifier><url>/11/4/</url></unit><unit id="79" label="chapter"><name>Noise Regulation</name><identifier>11</identifier><url>/11/</url></unit></ancestry><structure_contents><unit id="565"><structure_id>84</structure_id><section_number>114.01</section_number><catch_line>Vehicle Repairs.</catch_line><url>/114.01/</url><token>114.01</token></unit><unit id="2105"><structure_id>84</structure_id><section_number>114.02</section_number><catch_line>Motor Driven Vehicles.</catch_line><url>/114.02/</url><token>114.02</token></unit><unit id="3725"><structure_id>84</structure_id><section_number>114.03</section_number><catch_line>Vehicles &#x2013; Loading And Unloading.</catch_line><url>/114.03/</url><token>114.03</token></unit><unit id="2293"><structure_id>84</structure_id><section_number>114.04</section_number><catch_line>Audible Signaling Devices.</catch_line><url>/114.04/</url><token>114.04</token></unit><unit id="4133"><structure_id>84</structure_id><section_number>114.05</section_number><catch_line>Audible Advertising Devices &#x2013; Commercial Food Vendors.</catch_line><url>/114.05/</url><token>114.05</token></unit><unit id="389"><structure_id>84</structure_id><section_number>114.06</section_number><catch_line>Vehicle Theft Alarm Systems.</catch_line><url>/114.06/</url><token>114.06</token></unit><unit id="486"><structure_id>84</structure_id><section_number>114.07</section_number><catch_line>Audible Status Indicator.</catch_line><url>/114.07/</url><token>114.07</token></unit></structure_contents><next_section id="4133"><structure_id>84</structure_id><section_number>114.05</section_number><catch_line>Audible Advertising Devices &#x2013; Commercial Food Vendors.</catch_line><url>/114.05/</url><token>114.05</token></next_section><metadata></metadata><references></references><url>/114.04/</url><token>114.04</token><formats><txt>/114.04.txt</txt><json>/114.04.xml</json></formats><dublin_core><Title>Audible Signaling Devices.</Title><Type>Text</Type><Format>text/html</Format><Identifier>&#xA7; 114.04</Identifier><Relation>Los Angeles Municipal Code</Relation></dublin_core><plain_text>                            LOS ANGELES MUNICIPAL CODE

AUDIBLE SIGNALING DEVICES. (&#xA7; 114.04)

&#xA0; AUDIBLE SIGNALING DEVICES.
	(Added by Ord. No. 161,574, Eff. 9/8/86.)	It shall be unlawful for any person,
within any residential zone of the City or within 500 feet thereof, to sound,
blow, or operate any audible signaling device, including sequential airhorns or
electronically operated vehicular loud speaker music devices, which can be heard
for a distance greater than 200 feet for any purpose.&#xA0; Violation of this
section shall constitute an infraction&#xA0; This section does not address horn or
warning devices regulated in Article 1 of Chapter 5 of Division 12 of the
Vehicle Code of the State of California, commencing at Section 27000.&#xA0; (Last
sentence amended by Ord. No. 165.191, Eff. 10/23/89.)
</plain_text><html>
					&lt;section&gt;&lt;p&gt;&#xA0; AUDIBLE SIGNALING DEVICES.
	(Added by Ord. No. 161,574, Eff. 9/8/86.)&lt;br /&gt;&lt;br /&gt;	It shall be unlawful for any person, within any residential zone of the City or within 500 feet thereof, to sound, blow, or operate any audible signaling device, including sequential airhorns or electronically operated vehicular loud speaker music devices, which can be heard for a distance greater than 200 feet for any purpose.&#xA0; Violation of this section shall constitute an infraction&#xA0; This section does not address horn or warning devices regulated in Article 1 of Chapter 5 of Division 12 of the Vehicle Code of the State of California, commencing at Section 27000.&#xA0; (Last sentence amended by Ord. No. 165.191, Eff. 10/23/89.)&lt;/p&gt;&lt;/section&gt;</html><previous_section id="3725"><structure_id>84</structure_id><section_number>114.03</section_number><catch_line>Vehicles &#x2013; Loading And Unloading.</catch_line><url>/114.03/</url><token>114.03</token></previous_section><text><unit id="2273" prefix=""><text>&#xA0; AUDIBLE SIGNALING DEVICES.
	(Added by Ord. No. 161,574, Eff. 9/8/86.)	It shall be unlawful for any person, within any residential zone of the City or within 500 feet thereof, to sound, blow, or operate any audible signaling device, including sequential airhorns or electronically operated vehicular loud speaker music devices, which can be heard for a distance greater than 200 feet for any purpose.&#xA0; Violation of this section shall constitute an infraction&#xA0; This section does not address horn or warning devices regulated in Article 1 of Chapter 5 of Division 12 of the Vehicle Code of the State of California, commencing at Section 27000.&#xA0; (Last sentence amended by Ord. No. 165.191, Eff. 10/23/89.)</text><type>section</type><prefixes><unit></unit></prefixes><entire_prefix></entire_prefix><prefix_anchor></prefix_anchor><level>1</level></unit></text></law>
