<?xml version="1.0"?>
<law><section_number>19.14</section_number><edition_id>1</edition_id><section_id>1992</section_id><structure_id>78</structure_id><catch_line>Fees For Enforcement Of Housing Covenants.</catch_line><history></history><full_text>&#xA0; FEES FOR ENFORCEMENT OF HOUSING COVENANTS.
(Added by Ord. No. 179,681, Eff. 4/15/08.)

	The following fees shall be charged and collected by the Los Angeles Housing Department for the preparation and enforcement of the affordable housing covenants described in Section 12.22 A.25(h)(1) through (3) of this Code.</full_text><order_by>14</order_by><ancestry><unit id="78" label="article"><name>Fees</name><identifier>9</identifier><url>/1/9/</url></unit><unit id="7" label="chapter"><name>General Provisions and Zoning</name><identifier>1</identifier><url>/1/</url></unit></ancestry><structure_contents><unit id="1198"><structure_id>78</structure_id><section_number>19.00</section_number><catch_line>Filing Of Applications And Appeals.</catch_line><url>/19.00/</url><token>19.00</token></unit><unit id="3604"><structure_id>78</structure_id><section_number>19.01</section_number><catch_line>Filing Fee - Applications And Appeals.</catch_line><url>/19.01/</url><token>19.01</token></unit><unit id="3260"><structure_id>78</structure_id><section_number>19.02</section_number><catch_line>Filing Fees - Division Of Land And Private Street Maps And Appeals.</catch_line><url>/19.02/</url><token>19.02</token></unit><unit id="1848"><structure_id>78</structure_id><section_number>19.03</section_number><catch_line>Fees For General Plan Consistency.</catch_line><url>/19.03/</url><token>19.03</token></unit><unit id="1403"><structure_id>78</structure_id><section_number>19.04</section_number><catch_line>Filing Fee - Plans And Conditions Of Approval.</catch_line><url>/19.04/</url><token>19.04</token></unit><unit id="3255"><structure_id>78</structure_id><section_number>19.05</section_number><catch_line>Filing Fees For Environmental Clearances.</catch_line><url>/19.05/</url><token>19.05</token></unit><unit id="3837"><structure_id>78</structure_id><section_number>19.06</section_number><catch_line>Filing Fees For Coastal Development Permits.</catch_line><url>/19.06/</url><token>19.06</token></unit><unit id="294"><structure_id>78</structure_id><section_number>19.07</section_number><catch_line>Fees For Flood Hazard Reports And Compliance Checks.</catch_line><url>/19.07/</url><token>19.07</token></unit><unit id="3792"><structure_id>78</structure_id><section_number>19.08</section_number><catch_line>Surcharge For One-Stop Permit Center.</catch_line><url>/19.08/</url><token>19.08</token></unit><unit id="2482"><structure_id>78</structure_id><section_number>19.09</section_number><catch_line>Land Development Counseling &#x2013; Fee For Second And Subsequent Sessions.</catch_line><url>/19.09/</url><token>19.09</token></unit><unit id="2930"><structure_id>78</structure_id><section_number>19.10</section_number><catch_line>Development Agreement Fees.</catch_line><url>/19.10/</url><token>19.10</token></unit><unit id="3926"><structure_id>78</structure_id><section_number>19.11</section_number><catch_line>Annual Inspection Of Compliance With Far Averaging Covenant.</catch_line><url>/19.11/</url><token>19.11</token></unit><unit id="4061"><structure_id>78</structure_id><section_number>19.12</section_number><catch_line>Deviations Pursuant To Section 16.03 E.</catch_line><url>/19.12/</url><token>19.12</token></unit><unit id="2124"><structure_id>78</structure_id><section_number>19.13</section_number><catch_line>Surcharge For Automated Systems For The Department Of City Planning.</catch_line><url>/19.13/</url><token>19.13</token></unit><unit id="1992"><structure_id>78</structure_id><section_number>19.14</section_number><catch_line>Fees For Enforcement Of Housing Covenants.</catch_line><url>/19.14/</url><token>19.14</token></unit><unit id="1507"><structure_id>78</structure_id><section_number>19.15</section_number><catch_line>Department Of Transportation Traffic Study Review, Condition Clearance And Permit Issuance Fees.</catch_line><url>/19.15/</url><token>19.15</token></unit><unit id="2569"><structure_id>78</structure_id><section_number>19.16</section_number><catch_line>General Plan Maintenance Surcharge For The Department Of City Planning.</catch_line><url>/19.16/</url><token>19.16</token></unit></structure_contents><next_section id="1507"><structure_id>78</structure_id><section_number>19.15</section_number><catch_line>Department Of Transportation Traffic Study Review, Condition Clearance And Permit Issuance Fees.</catch_line><url>/19.15/</url><token>19.15</token></next_section><metadata></metadata><references></references><url>/19.14/</url><token>19.14</token><formats><txt>/19.14.txt</txt><json>/19.14.xml</json></formats><dublin_core><Title>Fees For Enforcement Of Housing Covenants.</Title><Type>Text</Type><Format>text/html</Format><Identifier>&#xA7; 19.14</Identifier><Relation>Los Angeles Municipal Code</Relation></dublin_core><plain_text>                            LOS ANGELES MUNICIPAL CODE

FEES FOR ENFORCEMENT OF HOUSING COVENANTS. (&#xA7; 19.14)

&#xA0; FEES FOR ENFORCEMENT OF HOUSING COVENANTS.
(Added by Ord. No. 179,681, Eff. 4/15/08.)	The following fees shall be charged
and collected by the Los Angeles Housing Department for the preparation and
enforcement of the affordable housing covenants described in Section 12.22
A.25(h)(1) through (3) of this Code.
</plain_text><html>
					&lt;section&gt;&lt;p&gt;&#xA0; FEES FOR ENFORCEMENT OF HOUSING COVENANTS.
(Added by Ord. No. 179,681, Eff. 4/15/08.)&lt;br /&gt;&lt;br /&gt;	The following fees shall be charged and collected by the Los Angeles Housing Department for the preparation and enforcement of the affordable housing covenants described in Section 12.22 A.25(h)(1) through (3) of this Code.&lt;/p&gt;&lt;/section&gt;</html><previous_section id="2124"><structure_id>78</structure_id><section_number>19.13</section_number><catch_line>Surcharge For Automated Systems For The Department Of City Planning.</catch_line><url>/19.13/</url><token>19.13</token></previous_section><text><unit id="1975" prefix=""><text>&#xA0; FEES FOR ENFORCEMENT OF HOUSING COVENANTS.
(Added by Ord. No. 179,681, Eff. 4/15/08.)	The following fees shall be charged and collected by the Los Angeles Housing Department for the preparation and enforcement of the affordable housing covenants described in Section 12.22 A.25(h)(1) through (3) of this Code.</text><type>section</type><prefixes><unit></unit></prefixes><entire_prefix></entire_prefix><prefix_anchor></prefix_anchor><level>1</level></unit></text></law>
