<?xml version="1.0"?>
<law><section_number>45.52</section_number><edition_id>1</edition_id><section_id>4091</section_id><structure_id>108</structure_id><catch_line>Prohibited Activities.</catch_line><history></history><full_text>&#xA0; PROHIBITED ACTIVITIES.
	(Added by Ord. No. 153,406, Eff. 3/8/80.):

	It shall be unlawful for any person having a housing accommodation for rent or lease, or any authorized agent or employee of such person, to do or attempt to do any of the following:

	A.	Refuse to rent or lease a housing accommodation, refuse to negotiate for the rental or lease of a housing accommodation, or otherwise deny to or withhold from, any person or persons, a housing accommodation on the basis of age, parenthood, pregnancy, or the potential or actual tenancy of a minor child.

	B.	Discriminate against any person in the terms, conditions, or privileges of the rental or lease of a housing accommodation, or in the provision of services, facilities, or benefits, in connection therewith, on the basis of age, parenthood, pregnancy, or the potential or actual tenancy of a minor child. However, nothing herein shall preclude any person from imposing restrictions on the use of common areas, facilities, and services which are reasonably necessary to protect the health and safety of a minor child.

	C.	Represent to any person on the basis of age, parenthood, pregnancy, or the potential or actual tenancy of a minor child that a housing accommodation is not available for inspection, rental, or lease when such housing accommodation is, in fact, available.

	D.	Make, print, or publish; or cause to be made, printed, or published any notice, statement, sign, advertisement, application, or contract with regard to a housing accommodation offered by that person that indicates any preference, limitation, or discrimination with respect to age, parenthood, pregnancy, or the potential or actual tenancy of a minor child.

	E.	Include in any rental agreement or lease for a housing accommodation, a clause or condition providing that as a condition of continued tenancy, the tenants shall remain childless or shall not bear children or otherwise not maintain a household with a person of a certain age.</full_text><order_by>52</order_by><ancestry><unit id="108" label="article"><name>
Prohibition Against Discrimination In Housing Based On Age</name><identifier>5.5</identifier><url>/4/5.5/</url></unit><unit id="11" label="chapter"><name>Public Welfare</name><identifier>4</identifier><url>/4/</url></unit></ancestry><structure_contents><unit id="3583"><structure_id>108</structure_id><section_number>45.50</section_number><catch_line>Findings And Purpose.</catch_line><url>/45.50/</url><token>45.50</token></unit><unit id="1548"><structure_id>108</structure_id><section_number>45.51</section_number><catch_line>Definitions.</catch_line><url>/45.51/</url><token>45.51</token></unit><unit id="4091"><structure_id>108</structure_id><section_number>45.52</section_number><catch_line>Prohibited Activities.</catch_line><url>/45.52/</url><token>45.52</token></unit><unit id="1770"><structure_id>108</structure_id><section_number>45.53</section_number><catch_line>Exemptions.</catch_line><url>/45.53/</url><token>45.53</token></unit><unit id="1746"><structure_id>108</structure_id><section_number>45.54</section_number><catch_line>Financial Obligations Requirements Not Prohibited.</catch_line><url>/45.54/</url><token>45.54</token></unit><unit id="639"><structure_id>108</structure_id><section_number>45.55</section_number><catch_line>Remedies.</catch_line><url>/45.55/</url><token>45.55</token></unit></structure_contents><next_section id="1770"><structure_id>108</structure_id><section_number>45.53</section_number><catch_line>Exemptions.</catch_line><url>/45.53/</url><token>45.53</token></next_section><metadata></metadata><references></references><url>/45.52/</url><token>45.52</token><formats><txt>/45.52.txt</txt><json>/45.52.xml</json></formats><dublin_core><Title>Prohibited Activities.</Title><Type>Text</Type><Format>text/html</Format><Identifier>&#xA7; 45.52</Identifier><Relation>Los Angeles Municipal Code</Relation></dublin_core><plain_text>                            LOS ANGELES MUNICIPAL CODE

PROHIBITED ACTIVITIES. (&#xA7; 45.52)

&#xA0; PROHIBITED ACTIVITIES.
	(Added by Ord. No. 153,406, Eff. 3/8/80.):	It shall be unlawful for any person
having a housing accommodation for rent or lease, or any authorized agent or
employee of such person, to do or attempt to do any of the following:	A.	Refuse
to rent or lease a housing accommodation, refuse to negotiate for the rental or
lease of a housing accommodation, or otherwise deny to or withhold from, any
person or persons, a housing accommodation on the basis of age, parenthood,
pregnancy, or the potential or actual tenancy of a minor child.	B.	Discriminate
against any person in the terms, conditions, or privileges of the rental or
lease of a housing accommodation, or in the provision of services, facilities,
or benefits, in connection therewith, on the basis of age, parenthood,
pregnancy, or the potential or actual tenancy of a minor child. However, nothing
herein shall preclude any person from imposing restrictions on the use of common
areas, facilities, and services which are reasonably necessary to protect the
health and safety of a minor child.	C.	Represent to any person on the basis of
age, parenthood, pregnancy, or the potential or actual tenancy of a minor child
that a housing accommodation is not available for inspection, rental, or lease
when such housing accommodation is, in fact, available.	D.	Make, print, or
publish; or cause to be made, printed, or published any notice, statement, sign,
advertisement, application, or contract with regard to a housing accommodation
offered by that person that indicates any preference, limitation, or
discrimination with respect to age, parenthood, pregnancy, or the potential or
actual tenancy of a minor child.	E.	Include in any rental agreement or lease for
a housing accommodation, a clause or condition providing that as a condition of
continued tenancy, the tenants shall remain childless or shall not bear children
or otherwise not maintain a household with a person of a certain age.
</plain_text><html>
					&lt;section&gt;&lt;p&gt;&#xA0; PROHIBITED ACTIVITIES.
	(Added by Ord. No. 153,406, Eff. 3/8/80.):&lt;br /&gt;&lt;br /&gt;	It shall be unlawful for any person having a housing accommodation for rent or lease, or any authorized agent or employee of such person, to do or attempt to do any of the following:&lt;br /&gt;&lt;br /&gt;	A.	Refuse to rent or lease a housing accommodation, refuse to negotiate for the rental or lease of a housing accommodation, or otherwise deny to or withhold from, any person or persons, a housing accommodation on the basis of age, parenthood, pregnancy, or the potential or actual tenancy of a &lt;span class="dictionary"&gt;minor&lt;/span&gt; child.&lt;br /&gt;&lt;br /&gt;	B.	Discriminate against any person in the terms, conditions, or &lt;span class="dictionary"&gt;privileges&lt;/span&gt; of the rental or lease of a housing accommodation, or in the provision of services, facilities, or benefits, in connection therewith, on the basis of age, parenthood, pregnancy, or the potential or actual tenancy of a &lt;span class="dictionary"&gt;minor&lt;/span&gt; child. However, nothing herein shall preclude any person from imposing restrictions on the use of common areas, facilities, and services which are reasonably necessary to protect the health and safety of a &lt;span class="dictionary"&gt;minor&lt;/span&gt; child.&lt;br /&gt;&lt;br /&gt;	C.	Represent to any person on the basis of age, parenthood, pregnancy, or the potential or actual tenancy of a &lt;span class="dictionary"&gt;minor&lt;/span&gt; child that a housing accommodation is not available for inspection, rental, or lease when such housing accommodation is, in &lt;span class="dictionary"&gt;fact&lt;/span&gt;, available.&lt;br /&gt;&lt;br /&gt;	D.	Make, print, or publish; or cause to be made, printed, or published any notice, statement, sign, advertisement, application, or &lt;span class="dictionary"&gt;contract&lt;/span&gt; with regard to a housing accommodation offered by that person that indicates any preference, limitation, or discrimination with respect to age, parenthood, pregnancy, or the potential or actual tenancy of a &lt;span class="dictionary"&gt;minor&lt;/span&gt; child.&lt;br /&gt;&lt;br /&gt;	E.	Include in any rental agreement or lease for a housing accommodation, a clause or condition providing that as a condition of continued tenancy, the tenants shall remain childless or shall not bear children or otherwise not maintain a household with a person of a certain age.&lt;/p&gt;&lt;/section&gt;</html><previous_section id="1548"><structure_id>108</structure_id><section_number>45.51</section_number><catch_line>Definitions.</catch_line><url>/45.51/</url><token>45.51</token></previous_section><text><unit id="4064" prefix=""><text>&#xA0; PROHIBITED ACTIVITIES.
	(Added by Ord. No. 153,406, Eff. 3/8/80.):	It shall be unlawful for any person having a housing accommodation for rent or lease, or any authorized agent or employee of such person, to do or attempt to do any of the following:	A.	Refuse to rent or lease a housing accommodation, refuse to negotiate for the rental or lease of a housing accommodation, or otherwise deny to or withhold from, any person or persons, a housing accommodation on the basis of age, parenthood, pregnancy, or the potential or actual tenancy of a minor child.	B.	Discriminate against any person in the terms, conditions, or privileges of the rental or lease of a housing accommodation, or in the provision of services, facilities, or benefits, in connection therewith, on the basis of age, parenthood, pregnancy, or the potential or actual tenancy of a minor child. However, nothing herein shall preclude any person from imposing restrictions on the use of common areas, facilities, and services which are reasonably necessary to protect the health and safety of a minor child.	C.	Represent to any person on the basis of age, parenthood, pregnancy, or the potential or actual tenancy of a minor child that a housing accommodation is not available for inspection, rental, or lease when such housing accommodation is, in fact, available.	D.	Make, print, or publish; or cause to be made, printed, or published any notice, statement, sign, advertisement, application, or contract with regard to a housing accommodation offered by that person that indicates any preference, limitation, or discrimination with respect to age, parenthood, pregnancy, or the potential or actual tenancy of a minor child.	E.	Include in any rental agreement or lease for a housing accommodation, a clause or condition providing that as a condition of continued tenancy, the tenants shall remain childless or shall not bear children or otherwise not maintain a household with a person of a certain age.</text><type>section</type><prefixes><unit></unit></prefixes><entire_prefix></entire_prefix><prefix_anchor></prefix_anchor><level>1</level></unit></text></law>
