<?xml version="1.0"?>
<law><section_number>49.5.12</section_number><edition_id>1</edition_id><section_id>2267</section_id><structure_id>93</structure_id><catch_line>Future Employment Of City Officials.</catch_line><history></history><full_text>&#xA0; FUTURE EMPLOYMENT OF CITY OFFICIALS.
	(Title and Section Amended by Ord. No. 168,057, Eff. 8/8/92.)

	A.	No member of the City Council or member of any board, commission, committee or other such voting body of any agency who is required to file statements of economic interest pursuant to the California Political Reform Act, shall directly or indirectly, knowingly or willfully negotiate the possibility of future employment with any person (other than a government agency) who has a matter within the regulatory, proprietary, or contractual jurisdiction of his or her agency currently pending before that officer or employee or before any body of which he or she is a voting member.

	B.	No other City official shall, directly or indirectly, knowingly or willfully negotiate the possibility of future employment with any person (other than a government agency) who has a matter within the regulatory, proprietary, or contractual jurisdiction of his or her agency currently pending before that officer or employee.

	C.	No person who has a matter pending before a City official, or before any body of which the official is a voting member shall, directly or indirectly, knowingly or willfully negotiate the possibility of future employment of that City official.

	D.	No City official shall make, participate in making or use his or her official position to influence a decision involving the interests of a person with whom he or she has an agreement concerning future employment.</full_text><order_by>5.12</order_by><ancestry><unit id="93" label="article"><name>Municipal Ethics And Conflicts Of Interest</name><identifier>9.5</identifier><url>/4/9.5/</url></unit><unit id="11" label="chapter"><name>Public Welfare</name><identifier>4</identifier><url>/4/</url></unit></ancestry><structure_contents><unit id="3582"><structure_id>93</structure_id><section_number>49.5.1</section_number><catch_line>Title, Findings And Purposes.</catch_line><url>/49.5.1/</url><token>49.5.1</token></unit><unit id="1305"><structure_id>93</structure_id><section_number>49.5.10</section_number><catch_line>Restrictions On Gifts And Travel Expenses.</catch_line><url>/49.5.10/</url><token>49.5.10</token></unit><unit id="1880"><structure_id>93</structure_id><section_number>49.5.11</section_number><catch_line>Lobbying Activities Of Current And Former City Officials.</catch_line><url>/49.5.11/</url><token>49.5.11</token></unit><unit id="2267"><structure_id>93</structure_id><section_number>49.5.12</section_number><catch_line>Future Employment Of City Officials.</catch_line><url>/49.5.12/</url><token>49.5.12</token></unit><unit id="3323"><structure_id>93</structure_id><section_number>49.5.13</section_number><catch_line>Participation Of Elective City Officers And Employees In Governmental Decisions.</catch_line><url>/49.5.13/</url><token>49.5.13</token></unit><unit id="2435"><structure_id>93</structure_id><section_number>49.5.14</section_number><catch_line>Application Of Requirements.</catch_line><url>/49.5.14/</url><token>49.5.14</token></unit><unit id="1460"><structure_id>93</structure_id><section_number>49.5.15</section_number><catch_line>Contract Bidder And Proposer Disclosure &#x2013; Political Contributions And Fundraising Activity.</catch_line><url>/49.5.15/</url><token>49.5.15</token></unit><unit id="3691"><structure_id>93</structure_id><section_number>49.5.16</section_number><catch_line>Disclosure By Elective Officers In Connection With Lobbying Interests And City Contractors.</catch_line><url>/49.5.16/</url><token>49.5.16</token></unit><unit id="2402"><structure_id>93</structure_id><section_number>49.5.17</section_number><catch_line>Commissioner Participation In Contracting Process.*</catch_line><url>/49.5.17/</url><token>49.5.17</token></unit><unit id="3455"><structure_id>93</structure_id><section_number>49.5.18</section_number><catch_line>Ethics Training.</catch_line><url>/49.5.18/</url><token>49.5.18</token></unit><unit id="3739"><structure_id>93</structure_id><section_number>49.5.19</section_number><catch_line>Enforcement.</catch_line><url>/49.5.19/</url><token>49.5.19</token></unit><unit id="2512"><structure_id>93</structure_id><section_number>49.5.2</section_number><catch_line>Definitions.</catch_line><url>/49.5.2/</url><token>49.5.2</token></unit><unit id="4181"><structure_id>93</structure_id><section_number>49.5.20</section_number><catch_line>Late Filing Penalties.</catch_line><url>/49.5.20/</url><token>49.5.20</token></unit><unit id="3183"><structure_id>93</structure_id><section_number>49.5.21</section_number><catch_line>Effect Of Campaign Money Laundering Violation On Contracts And Fee Waivers.</catch_line><url>/49.5.21/</url><token>49.5.21</token></unit><unit id="464"><structure_id>93</structure_id><section_number>49.5.22</section_number><catch_line>Authority Of Enact.</catch_line><url>/49.5.22/</url><token>49.5.22</token></unit><unit id="3441"><structure_id>93</structure_id><section_number>49.5.23</section_number><catch_line>Applicability Of Other Laws.</catch_line><url>/49.5.23/</url><token>49.5.23</token></unit><unit id="4076"><structure_id>93</structure_id><section_number>49.5.24</section_number><catch_line>Severability.</catch_line><url>/49.5.24/</url><token>49.5.24</token></unit><unit id="2092"><structure_id>93</structure_id><section_number>49.5.3</section_number><catch_line>Confidential Information.</catch_line><url>/49.5.3/</url><token>49.5.3</token></unit><unit id="1072"><structure_id>93</structure_id><section_number>49.5.4</section_number><catch_line>Protection Of Employees Against Retaliation For Reporting Fraud, Waste Or Misuse Of Office.</catch_line><url>/49.5.4/</url><token>49.5.4</token></unit><unit id="3548"><structure_id>93</structure_id><section_number>49.5.5</section_number><catch_line>Misuse Of City Position Or Resource.</catch_line><url>/49.5.5/</url><token>49.5.5</token></unit><unit id="1049"><structure_id>93</structure_id><section_number>49.5.6</section_number><catch_line>Disclosure Regarding Economic Interests And Other Outside Interests.</catch_line><url>/49.5.6/</url><token>49.5.6</token></unit><unit id="2731"><structure_id>93</structure_id><section_number>49.5.7</section_number><catch_line>Disclosure By Nominees.</catch_line><url>/49.5.7/</url><token>49.5.7</token></unit><unit id="3161"><structure_id>93</structure_id><section_number>49.5.8</section_number><catch_line>Divestiture Of Assets.</catch_line><url>/49.5.8/</url><token>49.5.8</token></unit><unit id="1323"><structure_id>93</structure_id><section_number>49.5.9</section_number><catch_line>Restrictions On Honoraria And Outside Earned Income.</catch_line><url>/49.5.9/</url><token>49.5.9</token></unit></structure_contents><next_section id="3323"><structure_id>93</structure_id><section_number>49.5.13</section_number><catch_line>Participation Of Elective City Officers And Employees In Governmental Decisions.</catch_line><url>/49.5.13/</url><token>49.5.13</token></next_section><metadata></metadata><references></references><url>/49.5.12/</url><token>49.5.12</token><formats><txt>/49.5.12.txt</txt><json>/49.5.12.xml</json></formats><dublin_core><Title>Future Employment Of City Officials.</Title><Type>Text</Type><Format>text/html</Format><Identifier>&#xA7; 49.5.12</Identifier><Relation>Los Angeles Municipal Code</Relation></dublin_core><plain_text>                            LOS ANGELES MUNICIPAL CODE

FUTURE EMPLOYMENT OF CITY OFFICIALS. (&#xA7; 49.5.12)

&#xA0; FUTURE EMPLOYMENT OF CITY OFFICIALS.
	(Title and Section Amended by Ord. No. 168,057, Eff. 8/8/92.)	A.	No member of
the City Council or member of any board, commission, committee or other such
voting body of any agency who is required to file statements of economic
interest pursuant to the California Political Reform Act, shall directly or
indirectly, knowingly or willfully negotiate the possibility of future
employment with any person (other than a government agency) who has a matter
within the regulatory, proprietary, or contractual jurisdiction of his or her
agency currently pending before that officer or employee or before any body of
which he or she is a voting member.	B.	No other City official shall, directly or
indirectly, knowingly or willfully negotiate the possibility of future
employment with any person (other than a government agency) who has a matter
within the regulatory, proprietary, or contractual jurisdiction of his or her
agency currently pending before that officer or employee.	C.	No person who has a
matter pending before a City official, or before any body of which the official
is a voting member shall, directly or indirectly, knowingly or willfully
negotiate the possibility of future employment of that City official.	D.	No City
official shall make, participate in making or use his or her official position
to influence a decision involving the interests of a person with whom he or she
has an agreement concerning future employment.
</plain_text><html>
					&lt;section&gt;&lt;p&gt;&#xA0; FUTURE EMPLOYMENT OF CITY OFFICIALS.
	(Title and Section Amended by Ord. No. 168,057, Eff. 8/8/92.)&lt;br /&gt;&lt;br /&gt;	A.	No member of the City Council or member of any board, commission, committee or other such voting body of any agency who is required to file statements of economic interest pursuant to the California Political Reform Act, shall directly or indirectly, knowingly or willfully negotiate the possibility of future employment with any person (other than a government agency) who has a matter within the regulatory, proprietary, or contractual &lt;span class="dictionary"&gt;jurisdiction&lt;/span&gt; of his or her agency currently pending before that officer or employee or before any body of which he or she is a voting member.&lt;br /&gt;&lt;br /&gt;	B.	No other City official shall, directly or indirectly, knowingly or willfully negotiate the possibility of future employment with any person (other than a government agency) who has a matter within the regulatory, proprietary, or contractual &lt;span class="dictionary"&gt;jurisdiction&lt;/span&gt; of his or her agency currently pending before that officer or employee.&lt;br /&gt;&lt;br /&gt;	C.	No person who has a matter pending before a City official, or before any body of which the official is a voting member shall, directly or indirectly, knowingly or willfully negotiate the possibility of future employment of that City official.&lt;br /&gt;&lt;br /&gt;	D.	No City official shall make, participate in making or use his or her official position to influence a decision involving the interests of a person with whom he or she has an agreement concerning future employment.&lt;/p&gt;&lt;/section&gt;</html><previous_section id="1880"><structure_id>93</structure_id><section_number>49.5.11</section_number><catch_line>Lobbying Activities Of Current And Former City Officials.</catch_line><url>/49.5.11/</url><token>49.5.11</token></previous_section><text><unit id="2247" prefix=""><text>&#xA0; FUTURE EMPLOYMENT OF CITY OFFICIALS.
	(Title and Section Amended by Ord. No. 168,057, Eff. 8/8/92.)	A.	No member of the City Council or member of any board, commission, committee or other such voting body of any agency who is required to file statements of economic interest pursuant to the California Political Reform Act, shall directly or indirectly, knowingly or willfully negotiate the possibility of future employment with any person (other than a government agency) who has a matter within the regulatory, proprietary, or contractual jurisdiction of his or her agency currently pending before that officer or employee or before any body of which he or she is a voting member.	B.	No other City official shall, directly or indirectly, knowingly or willfully negotiate the possibility of future employment with any person (other than a government agency) who has a matter within the regulatory, proprietary, or contractual jurisdiction of his or her agency currently pending before that officer or employee.	C.	No person who has a matter pending before a City official, or before any body of which the official is a voting member shall, directly or indirectly, knowingly or willfully negotiate the possibility of future employment of that City official.	D.	No City official shall make, participate in making or use his or her official position to influence a decision involving the interests of a person with whom he or she has an agreement concerning future employment.</text><type>section</type><prefixes><unit></unit></prefixes><entire_prefix></entire_prefix><prefix_anchor></prefix_anchor><level>1</level></unit></text></law>
