<?xml version="1.0"?>
<law><section_number>55.11</section_number><edition_id>1</edition_id><section_id>1800</section_id><structure_id>53</structure_id><catch_line>Requirements For Ammunition Sales.</catch_line><history></history><full_text>&#xA0; REQUIREMENTS FOR AMMUNITION SALES.
	(Title and Section Amended by Ord. No. 180,447, Eff. 2/2/09, Oper. 6/18/09.)

	(a)	&#x201C;Firearm Ammunition&#x201D; means any self-contained unit consisting of the case, primer, propellant charge, and projectile for use in pistols, revolvers, rifles, shot guns, or any other device designed to be used as a weapon from which is expelled a projectile by the force of explosion or other form of combustion. &#x201C;Firearm Ammunition&#x201D; shall not include blank ammunition used solely in the course of motion picture, television, video, or theatrical productions.

	(b)	The term &#x201C;vendor&#x201D;, as used in this section, shall mean any person who is engaged in the retail sale of firearm ammunition and retail firearms dealers.

	(c)	No vendor shall sell or otherwise transfer ownership of any firearm ammunition to any person other than those listed in subsection (g) without at the time of purchase recording the following information on a form to be prescribed by the Board of Police Commissioners:

	1.	the date of the transaction,

	2.	the name, address and date of birth of the transferee,

	3.	the transferee&#x2019;s drivers license or other identification number and the state in which it was issued,

	4.	the brand, type and amount of ammunition transferred,

	5.	the transferee&#x2019;s signature, and

	6.	the name of the sales person who processed the transaction.

	The vendor shall also at the time of purchase or transfer obtain the right thumb print of the purchaser or transferee on the above-referenced form.

	(d)	No vendor shall sell or otherwise transfer ownership of any firearm ammunition without complying with all requirements of subsection (c) in a face-to-face transaction.

	(e)	The records required by this section shall be maintained on the premises of the vendor for a period of not less than two (2) years from the date of the recorded transfer.&#xA0; Said records shall be subject to inspection at any time during normal business hours in accordance with the provisions of Section 103.14 of this Code.

	(f)	No person shall knowingly make a false entry in, or fail to make a required entry in, or fail to obtain the required thumb print, or fail to maintain in the required manner records prepared in accordance herewith.&#xA0; No person shall refuse to permit a police department employee to examine any record prepared in accordance with this section during any inspection conducted pursuant to this section, or refuse to permit the use of any record or information therefrom by the police department.

	(g)	The requirements of subsection (c) shall not apply when the purchaser is any of the following:

	1.	any person described in Section 12302 or 12322 of the Penal Code of the State of California.

	2.	any off-duty peace officer who displays proper agency identification which identifies him or her as an active peace officer.

	3.	any person who has been issued a permit to carry a concealed weapon under the authority of Section 12050 of the Penal Code of the State of California

	4.	any security guard licensed&#xA0; under the authority of&#xA0; Section 12033 of the Penal Code of the State of California.

	5.	any firearms dealer who has been issued a Federal Firearms License, a Certificate of Eligibility by the State of California and a Seller of Firearms Police Permit by the City of Los Angeles.

	6.	any firearm ammunition vendor who has been issued a Seller of Ammunition Police Permit by the City of Los Angeles.

	(h)	Violation of this section shall constitute a misdemeanor.</full_text><order_by>11</order_by><ancestry><unit id="53" label="article"><name>Firearms &#x2013; Dangerous Weapons</name><identifier>5</identifier><url>/5/5/</url></unit><unit id="9" label="chapter"><name>Public Safety and Protection</name><identifier>5</identifier><url>/5/</url></unit></ancestry><structure_contents><unit id="1598"><structure_id>53</structure_id><section_number>55.00</section_number><catch_line>Guns &#x2013; Permits.</catch_line><url>/55.00/</url><token>55.00</token></unit><unit id="1938"><structure_id>53</structure_id><section_number>55.01</section_number><catch_line>Concealed Weapons &#x2013; Permit.</catch_line><url>/55.01/</url><token>55.01</token></unit><unit id="3465"><structure_id>53</structure_id><section_number>55.02</section_number><catch_line>Concealed Weapons &#x2013; Permit &#x2013; Record.</catch_line><url>/55.02/</url><token>55.02</token></unit><unit id="1825"><structure_id>53</structure_id><section_number>55.03</section_number><catch_line>Concealed Weapons &#x2013; Permits &#x2013; Fee.</catch_line><url>/55.03/</url><token>55.03</token></unit><unit id="3869"><structure_id>53</structure_id><section_number>55.04</section_number><catch_line>Tear Gas Weapons &#x2013; Permits.</catch_line><url>/55.04/</url><token>55.04</token></unit><unit id="3978"><structure_id>53</structure_id><section_number>55.05</section_number><catch_line>Assault Weapons &#x2013; Sale Or Possession Prohibited.</catch_line><url>/55.05/</url><token>55.05</token></unit><unit id="1981"><structure_id>53</structure_id><section_number>55.06</section_number><catch_line>Use Of Bows And Arrows Prohibited.</catch_line><url>/55.06/</url><token>55.06</token></unit><unit id="654"><structure_id>53</structure_id><section_number>55.07</section_number><catch_line>Demonstration Equipment Prohibited.</catch_line><url>/55.07/</url><token>55.07</token></unit><unit id="1466"><structure_id>53</structure_id><section_number>55.08</section_number><catch_line>Glass Bottles On Public Property Prohibited.</catch_line><url>/55.08/</url><token>55.08</token></unit><unit id="125"><structure_id>53</structure_id><section_number>55.09</section_number><catch_line>Ammunition Sales.</catch_line><url>/55.09/</url><token>55.09</token></unit><unit id="2087"><structure_id>53</structure_id><section_number>55.10</section_number><catch_line>Carry Knives Or Daggers In Plain View Prohibited.</catch_line><url>/55.10/</url><token>55.10</token></unit><unit id="1800"><structure_id>53</structure_id><section_number>55.11</section_number><catch_line>Requirements For Ammunition Sales.</catch_line><url>/55.11/</url><token>55.11</token></unit><unit id="2443"><structure_id>53</structure_id><section_number>55.12</section_number><catch_line>Duty To Report Theft Or Loss Of Firearms; Exemptions.</catch_line><url>/55.12/</url><token>55.12</token></unit><unit id="3232"><structure_id>53</structure_id><section_number>55.12.1</section_number><catch_line>Disposal Of Firearms And Ammunition.</catch_line><url>/55.12.1/</url><token>55.12.1</token></unit><unit id="3722"><structure_id>53</structure_id><section_number>55.13</section_number><catch_line>Sale Of Ammunition Clips And Similar Devices.</catch_line><url>/55.13/</url><token>55.13</token></unit><unit id="553"><structure_id>53</structure_id><section_number>55.14</section_number><catch_line>Sale Or Purchase Of More Than One Handgun Within A Thirty Day Period Prohibited.</catch_line><url>/55.14/</url><token>55.14</token></unit><unit id="4150"><structure_id>53</structure_id><section_number>55.15</section_number><catch_line>Fingerprinting Of Firearms Purchasers.</catch_line><url>/55.15/</url><token>55.15</token></unit><unit id="3490"><structure_id>53</structure_id><section_number>55.16</section_number><catch_line>Sale Of Ultracompact Firearms Prohibited.</catch_line><url>/55.16/</url><token>55.16</token></unit><unit id="3024"><structure_id>53</structure_id><section_number>55.17</section_number><catch_line>Possession Of Gun Parts In Airports.</catch_line><url>/55.17/</url><token>55.17</token></unit><unit id="2680"><structure_id>53</structure_id><section_number>55.18</section_number><catch_line>Sale Of Large Caliber Firearms Prohibited.</catch_line><url>/55.18/</url><token>55.18</token></unit><unit id="1184"><structure_id>53</structure_id><section_number>55.19</section_number><catch_line>Sale Of Ammunition For Large Caliber Firearms Prohibited.</catch_line><url>/55.19/</url><token>55.19</token></unit><unit id="3754"><structure_id>53</structure_id><section_number>55.20</section_number><catch_line>False Or Secret Compartments In Vehicles To Hide
Firearms Or Destructive Devices.</catch_line><url>/55.20/</url><token>55.20</token></unit></structure_contents><next_section id="2443"><structure_id>53</structure_id><section_number>55.12</section_number><catch_line>Duty To Report Theft Or Loss Of Firearms; Exemptions.</catch_line><url>/55.12/</url><token>55.12</token></next_section><metadata></metadata><references></references><url>/55.11/</url><token>55.11</token><formats><txt>/55.11.txt</txt><json>/55.11.xml</json></formats><dublin_core><Title>Requirements For Ammunition Sales.</Title><Type>Text</Type><Format>text/html</Format><Identifier>&#xA7; 55.11</Identifier><Relation>Los Angeles Municipal Code</Relation></dublin_core><plain_text>                            LOS ANGELES MUNICIPAL CODE

REQUIREMENTS FOR AMMUNITION SALES. (&#xA7; 55.11)

&#xA0; REQUIREMENTS FOR AMMUNITION SALES.
	(Title and Section Amended by Ord. No. 180,447, Eff. 2/2/09, Oper.
6/18/09.)	(a)	&#x201C;Firearm Ammunition&#x201D; means any self-contained unit consisting
of the case, primer, propellant charge, and projectile for use in pistols,
revolvers, rifles, shot guns, or any other device designed to be used as a
weapon from which is expelled a projectile by the force of explosion or other
form of combustion. &#x201C;Firearm Ammunition&#x201D; shall not include blank ammunition
used solely in the course of motion picture, television, video, or theatrical
productions.	(b)	The term &#x201C;vendor&#x201D;, as used in this section, shall mean any
person who is engaged in the retail sale of firearm ammunition and retail
firearms dealers.	(c)	No vendor shall sell or otherwise transfer ownership of
any firearm ammunition to any person other than those listed in subsection (g)
without at the time of purchase recording the following information on a form to
be prescribed by the Board of Police Commissioners:	1.	the date of the
transaction,	2.	the name, address and date of birth of the transferee,	3.	the
transferee&#x2019;s drivers license or other identification number and the state in
which it was issued,	4.	the brand, type and amount of ammunition
transferred,	5.	the transferee&#x2019;s signature, and	6.	the name of the sales
person who processed the transaction.	The vendor shall also at the time of
purchase or transfer obtain the right thumb print of the purchaser or transferee
on the above-referenced form.	(d)	No vendor shall sell or otherwise transfer
ownership of any firearm ammunition without complying with all requirements of
subsection (c) in a face-to-face transaction.	(e)	The records required by this
section shall be maintained on the premises of the vendor for a period of not
less than two (2) years from the date of the recorded transfer.&#xA0; Said records
shall be subject to inspection at any time during normal business hours in
accordance with the provisions of Section 103.14 of this Code.	(f)	No person
shall knowingly make a false entry in, or fail to make a required entry in, or
fail to obtain the required thumb print, or fail to maintain in the required
manner records prepared in accordance herewith.&#xA0; No person shall refuse to
permit a police department employee to examine any record prepared in accordance
with this section during any inspection conducted pursuant to this section, or
refuse to permit the use of any record or information therefrom by the police
department.	(g)	The requirements of subsection (c) shall not apply when the
purchaser is any of the following:	1.	any person described in Section 12302 or
12322 of the Penal Code of the State of California.	2.	any off-duty peace
officer who displays proper agency identification which identifies him or her as
an active peace officer.	3.	any person who has been issued a permit to carry a
concealed weapon under the authority of Section 12050 of the Penal Code of the
State of California	4.	any security guard licensed&#xA0; under the authority of&#xA0;
Section 12033 of the Penal Code of the State of California.	5.	any firearms
dealer who has been issued a Federal Firearms License, a Certificate of
Eligibility by the State of California and a Seller of Firearms Police Permit by
the City of Los Angeles.	6.	any firearm ammunition vendor who has been issued a
Seller of Ammunition Police Permit by the City of Los Angeles.	(h)	Violation of
this section shall constitute a misdemeanor.
</plain_text><html>
					&lt;section&gt;&lt;p&gt;&#xA0; REQUIREMENTS FOR AMMUNITION SALES.
	(Title and Section Amended by Ord. No. 180,447, Eff. 2/2/09, Oper. 6/18/09.)&lt;br /&gt;&lt;br /&gt;	(a)	&#x201C;Firearm Ammunition&#x201D; means any self-contained unit consisting of the case, primer, propellant charge, and projectile for use in pistols, revolvers, rifles, shot guns, or any other device designed to be used as a weapon from which is expelled a projectile by the force of explosion or other form of combustion. &#x201C;Firearm Ammunition&#x201D; shall not include blank ammunition used solely in the course of &lt;span class="dictionary"&gt;motion&lt;/span&gt; picture, television, video, or theatrical productions.&lt;br /&gt;&lt;br /&gt;	(b)	The term &#x201C;vendor&#x201D;, as used in this section, shall mean any person who is engaged in the retail sale of firearm ammunition and retail firearms dealers.&lt;br /&gt;&lt;br /&gt;	(c)	No vendor shall sell or otherwise transfer ownership of any firearm ammunition to any person other than those listed in subsection (g) without at the time of purchase recording the following information on a form to be prescribed by the Board of Police Commissioners:&lt;br /&gt;&lt;br /&gt;	1.	the date of the transaction,&lt;br /&gt;&lt;br /&gt;	2.	the name, address and date of birth of the transferee,&lt;br /&gt;&lt;br /&gt;	3.	the transferee&#x2019;s drivers license or other identification number and the state in which it was issued,&lt;br /&gt;&lt;br /&gt;	4.	the brand, type and amount of ammunition transferred,&lt;br /&gt;&lt;br /&gt;	5.	the transferee&#x2019;s signature, and&lt;br /&gt;&lt;br /&gt;	6.	the name of the sales person who processed the transaction.&lt;br /&gt;&lt;br /&gt;	The vendor shall also at the time of purchase or transfer obtain the right thumb print of the purchaser or transferee on the above-referenced form.&lt;br /&gt;&lt;br /&gt;	(d)	No vendor shall sell or otherwise transfer ownership of any firearm ammunition without complying with all requirements of subsection (c) in a face-to-face transaction.&lt;br /&gt;&lt;br /&gt;	(e)	The records required by this section shall be maintained on the premises of the vendor for a period of not less than two (2) years from the date of the recorded transfer.&#xA0; Said records shall be subject to inspection at any time during normal business hours in accordance with the provisions of Section 103.14 of this Code.&lt;br /&gt;&lt;br /&gt;	(f)	No person shall knowingly make a false entry in, or fail to make a required entry in, or fail to obtain the required thumb print, or fail to maintain in the required manner records prepared in accordance herewith.&#xA0; No person shall refuse to permit a police department employee to examine any record prepared in accordance with this section during any inspection conducted pursuant to this section, or refuse to permit the use of any record or information therefrom by the police department.&lt;br /&gt;&lt;br /&gt;	(g)	The requirements of subsection (c) shall not apply when the purchaser is any of the following:&lt;br /&gt;&lt;br /&gt;	1.	any person described in Section 12302 or 12322 of the Penal Code of the State of California.&lt;br /&gt;&lt;br /&gt;	2.	any off-duty &lt;span class="dictionary"&gt;peace officer&lt;/span&gt; who displays proper agency identification which identifies him or her as an active &lt;span class="dictionary"&gt;peace officer&lt;/span&gt;.&lt;br /&gt;&lt;br /&gt;	3.	any person who has been issued a permit to carry a concealed weapon under the authority of Section 12050 of the Penal Code of the State of California&lt;br /&gt;&lt;br /&gt;	4.	any security guard licensed&#xA0; under the authority of&#xA0; Section 12033 of the Penal Code of the State of California.&lt;br /&gt;&lt;br /&gt;	5.	any firearms dealer who has been issued a Federal Firearms License, a Certificate of Eligibility by the State of California and a Seller of Firearms Police Permit by the City of Los Angeles.&lt;br /&gt;&lt;br /&gt;	6.	any firearm ammunition vendor who has been issued a Seller of Ammunition Police Permit by the City of Los Angeles.&lt;br /&gt;&lt;br /&gt;	(h)	Violation of this section shall constitute a &lt;span class="dictionary"&gt;misdemeanor&lt;/span&gt;.&lt;/p&gt;&lt;/section&gt;</html><previous_section id="2087"><structure_id>53</structure_id><section_number>55.10</section_number><catch_line>Carry Knives Or Daggers In Plain View Prohibited.</catch_line><url>/55.10/</url><token>55.10</token></previous_section><text><unit id="1784" prefix=""><text>&#xA0; REQUIREMENTS FOR AMMUNITION SALES.
	(Title and Section Amended by Ord. No. 180,447, Eff. 2/2/09, Oper. 6/18/09.)	(a)	&#x201C;Firearm Ammunition&#x201D; means any self-contained unit consisting of the case, primer, propellant charge, and projectile for use in pistols, revolvers, rifles, shot guns, or any other device designed to be used as a weapon from which is expelled a projectile by the force of explosion or other form of combustion. &#x201C;Firearm Ammunition&#x201D; shall not include blank ammunition used solely in the course of motion picture, television, video, or theatrical productions.	(b)	The term &#x201C;vendor&#x201D;, as used in this section, shall mean any person who is engaged in the retail sale of firearm ammunition and retail firearms dealers.	(c)	No vendor shall sell or otherwise transfer ownership of any firearm ammunition to any person other than those listed in subsection (g) without at the time of purchase recording the following information on a form to be prescribed by the Board of Police Commissioners:	1.	the date of the transaction,	2.	the name, address and date of birth of the transferee,	3.	the transferee&#x2019;s drivers license or other identification number and the state in which it was issued,	4.	the brand, type and amount of ammunition transferred,	5.	the transferee&#x2019;s signature, and	6.	the name of the sales person who processed the transaction.	The vendor shall also at the time of purchase or transfer obtain the right thumb print of the purchaser or transferee on the above-referenced form.	(d)	No vendor shall sell or otherwise transfer ownership of any firearm ammunition without complying with all requirements of subsection (c) in a face-to-face transaction.	(e)	The records required by this section shall be maintained on the premises of the vendor for a period of not less than two (2) years from the date of the recorded transfer.&#xA0; Said records shall be subject to inspection at any time during normal business hours in accordance with the provisions of Section 103.14 of this Code.	(f)	No person shall knowingly make a false entry in, or fail to make a required entry in, or fail to obtain the required thumb print, or fail to maintain in the required manner records prepared in accordance herewith.&#xA0; No person shall refuse to permit a police department employee to examine any record prepared in accordance with this section during any inspection conducted pursuant to this section, or refuse to permit the use of any record or information therefrom by the police department.	(g)	The requirements of subsection (c) shall not apply when the purchaser is any of the following:	1.	any person described in Section 12302 or 12322 of the Penal Code of the State of California.	2.	any off-duty peace officer who displays proper agency identification which identifies him or her as an active peace officer.	3.	any person who has been issued a permit to carry a concealed weapon under the authority of Section 12050 of the Penal Code of the State of California	4.	any security guard licensed&#xA0; under the authority of&#xA0; Section 12033 of the Penal Code of the State of California.	5.	any firearms dealer who has been issued a Federal Firearms License, a Certificate of Eligibility by the State of California and a Seller of Firearms Police Permit by the City of Los Angeles.	6.	any firearm ammunition vendor who has been issued a Seller of Ammunition Police Permit by the City of Los Angeles.	(h)	Violation of this section shall constitute a misdemeanor.</text><type>section</type><prefixes><unit></unit></prefixes><entire_prefix></entire_prefix><prefix_anchor></prefix_anchor><level>1</level></unit></text></law>
